ior/__init__.py
ior/config.py
ior/iorconfig.py
ior/iorsdk.py
ior/config/__init__.py
ior/config/consts.py
ior/config/contracts/Certificate.json
ior/config/contracts/Exchange.json
ior/config/contracts/PermissionControl.json
ior/config/contracts/RoleControl.json
ior/config/contracts/StoredNFT.json
ior/config/contracts/TZContractTemplate.json
ior/config/contracts/TZTemplateControl.json
ior/core/__init__.py
ior/core/certificate_service.py
ior/core/exchange_service.py
ior/core/hello_world_service.py
ior/core/permission_control_service.py
ior/core/role_control_service.py
ior/core/stored_nft_service.py
ior/core/tz_contract_template_service.py
ior/core/tz_template_control_service.py
ior/util/__init__.py
ior/util/certificate_utils.py
ior/util/result_utils.py
ior/util/web3_utils.py
tzspace-0.0.8.dist-info/LICENSE
tzspace-0.0.8.dist-info/METADATA
tzspace-0.0.8.dist-info/WHEEL
tzspace-0.0.8.dist-info/top_level.txt
tzspace-0.0.8.dist-info/RECORD
