Metadata-Version: 2.1
Name: tzspace
Version: 0.0.8
Summary: tzspace sdk for ior standard
Home-page: https://github.com/tzspace-ior/tzspacesdk
Author: Jie Guan
Author-email: jguanisme@163.com
Classifier: Programming Language :: Python :: 3
Classifier: License :: OSI Approved :: MIT License
Classifier: Operating System :: OS Independent
License-File: LICENSE
